README.md
setup.cfg
setup.py
aws_snappy.egg-info/PKG-INFO
aws_snappy.egg-info/SOURCES.txt
aws_snappy.egg-info/dependency_links.txt
aws_snappy.egg-info/requires.txt
aws_snappy.egg-info/top_level.txt
snappy/__init__.py
snappy/snappy.py
snappy/utils/__init__.py
snappy/utils/constants.py
snappy/utils/helper.py
snappy/utils/matcher.py
tests/__init__.py
tests/mock/__init__.py
tests/mock/test_classifier.py
tests/units/__init__.py
tests/units/test_helper.py
tests/units/test_matcher.py