Metadata-Version: 2.1
Name: aws-snappy
Version: 2.0
Summary: Snappy is a Python library that facilitates taking root volume snapshots from EC2 as well as other EBS volumes.
Home-page: https://github.com/mervin-hemaraju-cko/snappy
Author: Mervin Hemaraju
Author-email: mervin.hemaraju@checkout.com
License: UNKNOWN
Platform: UNKNOWN
Requires-Python: >=3.7
